{
  "name": "animated-spell-effects",
  "title": "Animated Spell Effects",
  "description": "A small, but growing collection of animated spell are for use with various VTT's in the top-down/overhead perspective. All files are in transparent webm format.",
  "author": "Jack Kerouac",
  "version": "0.4.8",
  "minimumCoreVersion": "0.5.5",
  "compatibleCoreVersion": "0.7.5",
  "url": "https://github.com/jackkerouac/animated-spell-effects",
  "manifest": "https://raw.githubusercontent.com/jackkerouac/animated-spell-effects/master/module.json",
  "download": "https://github.com/jackkerouac/animated-spell-effects/releases/download/v0.4.8/v0.4.8.zip"
}
